tztHytest/__init__.py
tztHytest/common.py
tztHytest/product.py
tztHytest/run.py
tztHytest/utils/__init__.py
tztHytest/utils/log.py
tztHytest/utils/report.css
tztHytest/utils/report.js
tztHytest/utils/runner.py
tztHytest/utils/signal.py
tztHytest-0.0.2.dist-info/LICENSE.txt
tztHytest-0.0.2.dist-info/METADATA
tztHytest-0.0.2.dist-info/WHEEL
tztHytest-0.0.2.dist-info/entry_points.txt
tztHytest-0.0.2.dist-info/top_level.txt
tztHytest-0.0.2.dist-info/RECORD
